setux/targets/__init__.py
setux/targets/base.py
setux/targets/local.py
setux/targets/remote_tpl.py
setux/targets/ssh.py
setux_targets-0.2511.0.dist-info/METADATA
setux_targets-0.2511.0.dist-info/WHEEL
setux_targets-0.2511.0.dist-info/top_level.txt
setux_targets-0.2511.0.dist-info/RECORD
