Metadata-Version: 2.2
Name: setux_targets
Version: 0.2511.0
Summary: System deployment
Author-email: Louis RIVIERE <louis@riviere.xyz>
License: MIT
Project-URL: pypi, https://pypi.org/project/setux-targets
Project-URL: repository, https://gitlab.com/dugres/setux_targets
Keywords: utility
Classifier: Development Status :: 3 - Alpha
Classifier: License :: OSI Approved :: MIT License
Classifier: Programming Language :: Python :: 3
Classifier: Operating System :: POSIX :: Linux
Classifier: Environment :: Console
Classifier: Intended Audience :: Developers
Classifier: Intended Audience :: Information Technology
Classifier: Intended Audience :: System Administrators
Classifier: Topic :: System :: Installation/Setup
Classifier: Topic :: System :: Systems Administration
Classifier: Topic :: Utilities
Requires-Dist: setux_core>=0.2507.2
